dejankify/__init__.py
dejankify/dependency_cleanup.py
dejankify/stdlib_check.py
tests/__init__.py
tests/conftest.py
tests/test_deps.py
tests/test_file.py
dejankify-0.1.1.dist-info/LICENSE
dejankify-0.1.1.dist-info/METADATA
dejankify-0.1.1.dist-info/WHEEL
dejankify-0.1.1.dist-info/entry_points.txt
dejankify-0.1.1.dist-info/top_level.txt
dejankify-0.1.1.dist-info/RECORD
