Metadata-Version: 2.1
Name: dejankify
Version: 0.1.1
Summary: A tool to help you find and remove unused imports in your python project.
Home-page: https://github.com/JoshCLWren/dejankify
Author: Josh Wren
Author-email: joshisplutar@gmail.com
Classifier: Programming Language :: Python :: 3.11
Classifier: License :: OSI Approved :: MIT License
Classifier: Operating System :: OS Independent
Classifier: Development Status :: 3 - Alpha
Classifier: Intended Audience :: Developers
Requires-Python: >=3.11
License-File: LICENSE
Requires-Dist: pip
Requires-Dist: setuptools
Requires-Dist: wheel
Requires-Dist: pdbpp
Requires-Dist: black
Requires-Dist: flake8
Requires-Dist: isort
Requires-Dist: pylint
Requires-Dist: pydocstyle
Requires-Dist: mypy
Requires-Dist: fancycompleter
Requires-Dist: click
Requires-Dist: typing-extensions
Requires-Dist: astroid
Requires-Dist: dill
Requires-Dist: mccabe
Requires-Dist: tomlkit
Requires-Dist: pytest
Requires-Dist: argparse
Requires-Dist: pluggy
Requires-Dist: iniconfig
Requires-Dist: attrs
